rrcf/__init__.py
rrcf/rrcf.py
rrcf/shingle.py
hccf-0.2.dist-info/LICENSE
hccf-0.2.dist-info/METADATA
hccf-0.2.dist-info/WHEEL
hccf-0.2.dist-info/top_level.txt
hccf-0.2.dist-info/RECORD
